hwxml/__init__.py
hwxml/parser/__init__.py
hwxml/parser/models.py
hwxml/parser/parse_special.py
hwxml/parser/parse_trigger.py
hwxml/parser/parser.py
hwxml-1.1.1.dist-info/LICENSE
hwxml-1.1.1.dist-info/METADATA
hwxml-1.1.1.dist-info/WHEEL
hwxml-1.1.1.dist-info/top_level.txt
hwxml-1.1.1.dist-info/RECORD
