Metadata-Version: 2.1
Name: hwxml
Version: 1.1.1
Summary: Parse Happy Wheels XML
Home-page: https://github.com/kittenswolf/hwxml
Author: kittenswolf
License: UNKNOWN
Project-URL: Bug Reports, https://github.com/kittenswolf/hwxml/issues
Project-URL: Source, https://github.com/kittenswolf/hwxml/
Platform: UNKNOWN
Requires-Dist: beautifulsoup4
